odataormpy/__init__.py
odataormpy/exception/__init__.py
odataormpy/exception/exception.py
odataormpy/orm/__init__.py
odataormpy/orm/orm.py
odataormpy/orm/orm_expression.py
odataormpy/orm/orm_field.py
odataormpy/orm/orm_object.py
odataormpy/session/__init__.py
odataormpy/session/session.py
odataormpy-0.1.1.dist-info/licenses/LICENSE
odataormpy-0.1.1.dist-info/METADATA
odataormpy-0.1.1.dist-info/WHEEL
odataormpy-0.1.1.dist-info/top_level.txt
odataormpy-0.1.1.dist-info/RECORD
